[
  {
    "name":"com.bloxbean.cardano.yaci.store.governance.storage.impl.mapper.CommitteeDeRegistrationMapperImpl",
    "allDeclaredConstructors": true,
    "allDeclaredMethods": true,
    "allDeclaredFields": true
  },
  {
    "name":"com.bloxbean.cardano.yaci.store.governance.storage.impl.mapper.CommitteeDeRegistrationMapperImpl",
    "allDeclaredConstructors": true,
    "allDeclaredMethods": true,
    "allDeclaredFields": true
  },
  {
    "name":"com.bloxbean.cardano.yaci.store.governance.storage.impl.mapper.CommitteeMemberMapperImpl",
    "allDeclaredConstructors": true,
    "allDeclaredMethods": true,
    "allDeclaredFields": true
  },
  {
    "name":"com.bloxbean.cardano.yaci.store.governance.storage.impl.mapper.CommitteeRegistrationMapperImpl",
    "allDeclaredConstructors": true,
    "allDeclaredMethods": true,
    "allDeclaredFields": true
  },
  {
    "name":"com.bloxbean.cardano.yaci.store.governance.storage.impl.mapper.DRepRegistrationMapper",
    "allDeclaredConstructors": true,
    "allDeclaredMethods": true,
    "allDeclaredFields": true
  },
  {
    "name":"com.bloxbean.cardano.yaci.store.governance.storage.impl.mapper.DRepRegistrationMapperImpl",
    "allDeclaredConstructors": true,
    "allDeclaredMethods": true,
    "allDeclaredFields": true
  },
  {
    "name":"com.bloxbean.cardano.yaci.store.governance.storage.impl.mapper.DelegationVoteMapperImpl",
    "allDeclaredConstructors": true,
    "allDeclaredMethods": true,
    "allDeclaredFields": true
  },
  {
    "name":"com.bloxbean.cardano.yaci.store.governance.storage.impl.mapper.GovActionProposalMapperImpl",
    "allDeclaredConstructors": true,
    "allDeclaredMethods": true,
    "allDeclaredFields": true
  },
  {
    "name":"com.bloxbean.cardano.yaci.store.governance.storage.impl.mapper.VotingProcedureMapperImpl",
    "allDeclaredConstructors": true,
    "allDeclaredMethods": true,
    "allDeclaredFields": true
  },


  {
    "name": "com.bloxbean.cardano.yaci.store.governance.jooq.tables.pojos.Committee",
    "allDeclaredConstructors": true,
    "allDeclaredMethods": true,
    "allDeclaredFields": true
  },
  {
    "name": "com.bloxbean.cardano.yaci.store.governance.jooq.tables.pojos.CommitteeDeregistration",
    "allDeclaredConstructors": true,
    "allDeclaredMethods": true,
    "allDeclaredFields": true
  },
  {
    "name": "com.bloxbean.cardano.yaci.store.governance.jooq.tables.pojos.CommitteeMember",
    "allDeclaredConstructors": true,
    "allDeclaredMethods": true,
    "allDeclaredFields": true
  },
  {
    "name": "com.bloxbean.cardano.yaci.store.governance.jooq.tables.pojos.CommitteeRegistration",
    "allDeclaredConstructors": true,
    "allDeclaredMethods": true,
    "allDeclaredFields": true
  },
  {
    "name": "com.bloxbean.cardano.yaci.store.governance.jooq.tables.pojos.Constitution",
    "allDeclaredConstructors": true,
    "allDeclaredMethods": true,
    "allDeclaredFields": true
  },
  {
    "name": "com.bloxbean.cardano.yaci.store.governance.jooq.tables.pojos.DelegationVote",
    "allDeclaredConstructors": true,
    "allDeclaredMethods": true,
    "allDeclaredFields": true
  },
  {
    "name": "com.bloxbean.cardano.yaci.store.governance.jooq.tables.pojos.DrepRegistration",
    "allDeclaredConstructors": true,
    "allDeclaredMethods": true,
    "allDeclaredFields": true
  },
  {
    "name": "com.bloxbean.cardano.yaci.store.governance.jooq.tables.pojos.GovActionProposal",
    "allDeclaredConstructors": true,
    "allDeclaredMethods": true,
    "allDeclaredFields": true
  },
  {
    "name": "com.bloxbean.cardano.yaci.store.governance.jooq.tables.pojos.LocalCommittee",
    "allDeclaredConstructors": true,
    "allDeclaredMethods": true,
    "allDeclaredFields": true
  },
  {
    "name": "com.bloxbean.cardano.yaci.store.governance.jooq.tables.pojos.LocalCommitteeMember",
    "allDeclaredConstructors": true,
    "allDeclaredMethods": true,
    "allDeclaredFields": true
  },
  {
    "name": "com.bloxbean.cardano.yaci.store.governance.jooq.tables.pojos.LocalConstitution",
    "allDeclaredConstructors": true,
    "allDeclaredMethods": true,
    "allDeclaredFields": true
  },
  {
    "name": "com.bloxbean.cardano.yaci.store.governance.jooq.tables.pojos.LocalDrepDist",
    "allDeclaredConstructors": true,
    "allDeclaredMethods": true,
    "allDeclaredFields": true
  },
  {
    "name": "com.bloxbean.cardano.yaci.store.governance.jooq.tables.pojos.LocalGovActionProposalStatus",
    "allDeclaredConstructors": true,
    "allDeclaredMethods": true,
    "allDeclaredFields": true
  },
  {
    "name": "com.bloxbean.cardano.yaci.store.governance.jooq.tables.pojos.LocalHardForkInitiation",
    "allDeclaredConstructors": true,
    "allDeclaredMethods": true,
    "allDeclaredFields": true
  },
  {
    "name": "com.bloxbean.cardano.yaci.store.governance.jooq.tables.pojos.LocalTreasuryWithdrawal",
    "allDeclaredConstructors": true,
    "allDeclaredMethods": true,
    "allDeclaredFields": true
  },
  {
    "name": "com.bloxbean.cardano.yaci.store.governance.jooq.tables.pojos.VotingProcedure",
    "allDeclaredConstructors": true,
    "allDeclaredMethods": true,
    "allDeclaredFields": true
  },
  {
    "name": "com.bloxbean.cardano.yaci.store.governance.jooq.tables.pojos.Drep",
    "allPublicConstructors": true,
    "allPublicFields": true,
    "allDeclaredMethods": true
  },

  {
    "name": "com.bloxbean.cardano.yaci.core.model.governance.actions.GovAction",
    "allDeclaredConstructors": true,
    "allDeclaredMethods": true,
    "allDeclaredFields": true
  },
  {
    "name": "com.bloxbean.cardano.yaci.core.model.governance.actions.HardForkInitiationAction",
    "allDeclaredConstructors": true,
    "allDeclaredMethods": true,
    "allDeclaredFields": true
  },
  {
    "name": "com.bloxbean.cardano.yaci.core.model.governance.actions.InfoAction",
    "allDeclaredConstructors": true,
    "allDeclaredMethods": true,
    "allDeclaredFields": true
  },
  {
    "name": "com.bloxbean.cardano.yaci.core.model.governance.actions.NewConstitution",
    "allDeclaredConstructors": true,
    "allDeclaredMethods": true,
    "allDeclaredFields": true
  },
  {
    "name": "com.bloxbean.cardano.yaci.core.model.governance.actions.NoConfidence",
    "allDeclaredConstructors": true,
    "allDeclaredMethods": true,
    "allDeclaredFields": true
  },
  {
    "name": "com.bloxbean.cardano.yaci.core.model.governance.actions.ParameterChangeAction",
    "allDeclaredConstructors": true,
    "allDeclaredMethods": true,
    "allDeclaredFields": true
  },
  {
    "name": "com.bloxbean.cardano.yaci.core.model.governance.actions.TreasuryWithdrawalsAction",
    "allDeclaredConstructors": true,
    "allDeclaredMethods": true,
    "allDeclaredFields": true
  },
  {
    "name": "com.bloxbean.cardano.yaci.core.model.governance.actions.UpdateCommittee",
    "allDeclaredConstructors": true,
    "allDeclaredMethods": true,
    "allDeclaredFields": true
  },
  {
    "name": "com.bloxbean.cardano.yaci.core.model.governance.Anchor",
    "allDeclaredConstructors": true,
    "allDeclaredMethods": true,
    "allDeclaredFields": true
  },



  {
    "name": "com.bloxbean.cardano.yaci.core.model.governance.Committee",
    "allDeclaredConstructors": true,
    "allDeclaredMethods": true,
    "allDeclaredFields": true
  },
  {
    "name": "com.bloxbean.cardano.yaci.core.model.governance.Constitution",
    "allDeclaredConstructors": true,
    "allDeclaredMethods": true,
    "allDeclaredFields": true
  },
  {
    "name": "com.bloxbean.cardano.yaci.core.model.governance.Drep",
    "allDeclaredConstructors": true,
    "allDeclaredMethods": true,
    "allDeclaredFields": true
  },
  {
    "name": "com.bloxbean.cardano.yaci.core.model.governance.DrepType",
    "allDeclaredConstructors": true,
    "allDeclaredMethods": true,
    "allDeclaredFields": true
  },
  {
    "name": "com.bloxbean.cardano.yaci.core.model.governance.GovActionId",
    "allDeclaredConstructors": true,
    "allDeclaredMethods": true,
    "allDeclaredFields": true
  },
  {
    "name": "com.bloxbean.cardano.yaci.core.model.governance.GovActionType",
    "allDeclaredConstructors": true,
    "allDeclaredMethods": true,
    "allDeclaredFields": true
  },
  {
    "name": "com.bloxbean.cardano.yaci.core.model.governance.ProposalProcedure",
    "allDeclaredConstructors": true,
    "allDeclaredMethods": true,
    "allDeclaredFields": true
  },
  {
    "name": "com.bloxbean.cardano.yaci.core.model.governance.Vote",
    "allDeclaredConstructors": true,
    "allDeclaredMethods": true,
    "allDeclaredFields": true
  },
  {
    "name": "com.bloxbean.cardano.yaci.core.model.governance.Voter",
    "allDeclaredConstructors": true,
    "allDeclaredMethods": true,
    "allDeclaredFields": true
  },
  {
    "name": "com.bloxbean.cardano.yaci.core.model.governance.VoterType",
    "allDeclaredConstructors": true,
    "allDeclaredMethods": true,
    "allDeclaredFields": true
  },
  {
    "name": "com.bloxbean.cardano.yaci.core.model.governance.VotingProcedure",
    "allDeclaredConstructors": true,
    "allDeclaredMethods": true,
    "allDeclaredFields": true
  },
  {
    "name": "com.bloxbean.cardano.yaci.core.model.governance.VotingProcedures",
    "allDeclaredConstructors": true,
    "allDeclaredMethods": true,
    "allDeclaredFields": true
  },


  {
    "name": "com.bloxbean.cardano.yaci.core.model.ProtocolVersion",
    "allDeclaredConstructors": true,
    "allDeclaredMethods": true,
    "allDeclaredFields": true
  },
  {
    "name": "com.bloxbean.cardano.yaci.core.model.Credential",
    "allDeclaredConstructors": true,
    "allDeclaredMethods": true,
    "allDeclaredFields": true
  },
  {
    "name": "com.bloxbean.cardano.yaci.core.model.ProtocolParamUpdate",
    "allDeclaredConstructors": true,
    "allDeclaredMethods": true,
    "allDeclaredFields": true
  },
  {
    "name": "com.bloxbean.cardano.yaci.core.model.PoolVotingThresholds",
    "allDeclaredConstructors": true,
    "allDeclaredMethods": true,
    "allDeclaredFields": true
  },
  {
    "name": "com.bloxbean.cardano.yaci.core.model.DrepVoteThresholds",
    "allDeclaredConstructors": true,
    "allDeclaredMethods": true,
    "allDeclaredFields": true
  }
]
